better_exceptions_hook.pth
better_exceptions/__init__.py
better_exceptions/__main__.py
better_exceptions/color.py
better_exceptions/formatter.py
better_exceptions/log.py
better_exceptions/repl.py
better_exceptions/integrations/__init__.py
better_exceptions/integrations/django.py
better_exceptions_xl0-0.4.3.dist-info/licenses/LICENSE.txt
better_exceptions_xl0-0.4.3.dist-info/METADATA
better_exceptions_xl0-0.4.3.dist-info/WHEEL
better_exceptions_xl0-0.4.3.dist-info/top_level.txt
better_exceptions_xl0-0.4.3.dist-info/RECORD
