Metadata-Version: 2.4
Name: better_exceptions-xl0
Version: 0.4.3
Summary: Pretty and helpful exceptions, automatically
Author-email: Josh Junon <pypi@josh.junon.me>
License: MIT
Project-URL: Homepage, https://github.com/qix-/better-exceptions
Project-URL: Repository, https://github.com/qix-/better-exceptions
Project-URL: Download, https://github.com/qix-/better-exceptions/releases
Keywords: pretty,better,exceptions,exception,error,local,debug,debugging,locals
Classifier: Development Status :: 4 - Beta
Classifier: Intended Audience :: Developers
Classifier: Programming Language :: Python :: 3
Classifier: Programming Language :: Python :: 3.7
Classifier: Programming Language :: Python :: 3.8
Classifier: Programming Language :: Python :: 3.9
Classifier: Programming Language :: Python :: 3.10
Classifier: Programming Language :: Python :: 3.11
Classifier: Programming Language :: Python :: 3.12
Classifier: Programming Language :: Python :: 3.13
Classifier: Topic :: Software Development :: Debuggers
Requires-Python: >=3.7
License-File: LICENSE.txt
Requires-Dist: colorama; sys_platform == "win32"
Dynamic: license-file
